PyInstaller-stubs/METADATA.toml
PyInstaller-stubs/__init__.pyi
PyInstaller-stubs/__main__.pyi
PyInstaller-stubs/compat.pyi
PyInstaller-stubs/py.typed
PyInstaller-stubs/building/__init__.pyi
PyInstaller-stubs/building/api.pyi
PyInstaller-stubs/building/build_main.pyi
PyInstaller-stubs/building/datastruct.pyi
PyInstaller-stubs/building/splash.pyi
PyInstaller-stubs/depend/__init__.pyi
PyInstaller-stubs/depend/analysis.pyi
PyInstaller-stubs/depend/imphookapi.pyi
PyInstaller-stubs/isolated/__init__.pyi
PyInstaller-stubs/isolated/_parent.pyi
PyInstaller-stubs/lib/__init__.pyi
PyInstaller-stubs/lib/modulegraph/__init__.pyi
PyInstaller-stubs/lib/modulegraph/modulegraph.pyi
PyInstaller-stubs/utils/__init__.pyi
PyInstaller-stubs/utils/hooks/__init__.pyi
PyInstaller-stubs/utils/hooks/conda.pyi
PyInstaller-stubs/utils/win32/versioninfo.pyi
pyi_splash-stubs/METADATA.toml
pyi_splash-stubs/__init__.pyi
pyi_splash-stubs/py.typed
types_pyinstaller-6.16.0.20250918.dist-info/licenses/LICENSE
types_pyinstaller-6.16.0.20250918.dist-info/METADATA
types_pyinstaller-6.16.0.20250918.dist-info/WHEEL
types_pyinstaller-6.16.0.20250918.dist-info/top_level.txt
types_pyinstaller-6.16.0.20250918.dist-info/RECORD
